LICENSE
MANIFEST.in
setup.cfg
setup.py
alert360/__init__.py
alert360/actions.py
alert360/admin.py
alert360/apps.py
alert360/datasources.py
alert360/methods.py
alert360/models.py
alert360/tests.py
alert360/views.py
alert360.egg-info/PKG-INFO
alert360.egg-info/SOURCES.txt
alert360.egg-info/dependency_links.txt
alert360.egg-info/requires.txt
alert360.egg-info/top_level.txt
alert360/js/README.MD
alert360/js/list_config.js
alert360/management/__init__.py
alert360/management/__pycache__/__init__.cpython-310.pyc
alert360/management/commands/__init__.py
alert360/management/commands/runwatcher.py
alert360/management/commands/__pycache__/__init__.cpython-310.pyc
alert360/management/commands/__pycache__/runwatcher.cpython-310.pyc
alert360/migrations/0001_initial.py
alert360/migrations/__init__.py
alert360/migrations/__pycache__/0001_initial.cpython-310.pyc
alert360/migrations/__pycache__/0002_auto_20220803_1721.cpython-310.pyc
alert360/migrations/__pycache__/0003_statewatcher_name.cpython-310.pyc
alert360/migrations/__pycache__/__init__.cpython-310.pyc
djangoproject/__init__.py
djangoproject/asgi.py
djangoproject/settings.py
djangoproject/urls.py
djangoproject/wsgi.py